app.py
conf/__init__.py
conf/backup_settings.py
conf/docker_mirrors.py
conf/i18n_settings.py
conf/install_settings.py
data/en_US/messages.py
data/zh_CN/messages.py
module/backup.py
module/install.py
module/replace_env_vars.py
module/update.py
nekro_agent_toolkit-1.5.5.dist-info/licenses/LICENSE
scripts/sort_messages.py
tools/backup_docker_images.py
tools/dangling_image_clean.py
tools/docker_mirror_setup.py
tools/docker_mirror_setup_release.py
tools/import_docker_images.py
tools/permission_setup.py
utils/backup_utils.py
utils/docker_helpers.py
utils/helpers.py
utils/i18n.py
utils/install_utils.py
utils/update_utils.py
nekro_agent_toolkit-1.5.5.dist-info/METADATA
nekro_agent_toolkit-1.5.5.dist-info/WHEEL
nekro_agent_toolkit-1.5.5.dist-info/entry_points.txt
nekro_agent_toolkit-1.5.5.dist-info/top_level.txt
nekro_agent_toolkit-1.5.5.dist-info/RECORD
