Metadata-Version: 2.4
Name: nekro-agent-toolkit
Version: 1.5.5
Summary: Nekro Agent 安装、更新与备份的统一管理工具
Home-page: https://github.com/greenhandzdl/nekro-agent-toolkit
Author: greenhandzdl
Author-email: greenhandzdl@greenhandzdl.moe
License: MIT
Project-URL: Homepage, https://github.com/greenhandzdl/nekro-agent-toolkit
Classifier: Development Status :: 4 - Beta
Classifier: Intended Audience :: Developers
Classifier: License :: OSI Approved :: MIT License
Classifier: Operating System :: POSIX :: Linux
Classifier: Programming Language :: Python :: 3
Classifier: Programming Language :: Python :: 3.8
Classifier: Programming Language :: Python :: 3.9
Classifier: Programming Language :: Python :: 3.10
Classifier: Programming Language :: Python :: 3.11
Requires-Python: >=3.6
License-File: LICENSE
Dynamic: author-email
Dynamic: home-page
Dynamic: license-file
Dynamic: requires-python
